django_trim-0.4.4.dist-info/licenses/LICENSE
trim/__init__.py
trim/admin.py
trim/apps.py
trim/conf.py
trim/context.py
trim/cuts.py
trim/execute.py
trim/merge.py
trim/names.py
trim/oven.py
trim/perms.py
trim/rand.py
trim/response.py
trim/shorts.py
trim/signals.py
trim/strings.py
trim/tests.py
trim/urls.py
trim/account/admin.py
trim/account/apps.py
trim/account/dispatch.py
trim/account/forms.py
trim/account/models.py
trim/account/signals.py
trim/account/tests.py
trim/account/urls.py
trim/account/migrations/0001_initial.py
trim/account/migrations/0002_accountemail_account_verified_and_more.py
trim/account/migrations/0003_alter_account_user.py
trim/account/migrations/0004_forgotpasswordrecord.py
trim/account/migrations/0005_accountemail_user.py
trim/account/migrations/0006_alter_accountemail_user.py
trim/account/migrations/0007_accountemail_uuid_token.py
trim/account/migrations/0008_emailinvite.py
trim/account/migrations/0009_alter_account_user.py
trim/account/migrations/0010_alter_account_user_alter_emailinvite_user.py
trim/account/migrations/__init__.py
trim/account/templates/account/accountemail_form.html
trim/account/templates/account/base.html
trim/account/templates/account/emailinvite_form.html
trim/account/templates/account/emailinvite_list.html
trim/account/templates/account/forgotpasswordrecord_form.html
trim/account/templates/account/inactive.html
trim/account/templates/account/logged-out.html
trim/account/templates/account/login.html
trim/account/templates/account/password_update_form.html
trim/account/templates/account/profile.html
trim/account/templates/account/profile_form.html
trim/account/templates/account/sub/login_form.html
trim/account/templates/account/sub/login_prompt.html
trim/account/templates/account/sub/primary_login_form.html
trim/account/templates/account/sub/register_button.html
trim/account/templates/account/sub/social_buttons.html
trim/account/templates/account_backup/accountemail_form.html
trim/account/templates/account_backup/base.html
django_trim-0.4.4.dist-info/METADATA
django_trim-0.4.4.dist-info/WHEEL
django_trim-0.4.4.dist-info/entry_points.txt
django_trim-0.4.4.dist-info/top_level.txt
django_trim-0.4.4.dist-info/RECORD
