Metadata-Version: 2.4
Name: django-trim
Version: 0.4.4
Summary: Django trim is a facade to the common features of Django providing a layer of sugar for all those daily components.
Author-email: Strangemother <django-trim@strangemother.com>
License: MIT
Project-URL: Homepage, http://github.com/strangemother/django-trim
Project-URL: Bug Tracker, http://github.com/strangemother/django-trim/issues
Classifier: Programming Language :: Python :: 3
Classifier: License :: OSI Approved :: MIT License
Classifier: Operating System :: OS Independent
Requires-Python: >=3.7
License-File: LICENSE
Requires-Dist: loguru
Provides-Extra: docs
Requires-Dist: trimdocs>=0.1.0a0; extra == "docs"
Provides-Extra: test
Requires-Dist: pytest>=7.0.0; extra == "test"
Requires-Dist: pytest-django>=4.5.0; extra == "test"
Requires-Dist: pytest-cov>=4.0.0; extra == "test"
Requires-Dist: pytest-xdist>=3.0.0; extra == "test"
Requires-Dist: coverage[toml]>=7.0.0; extra == "test"
Dynamic: license-file
